saferax/__init__.py
saferax/load.py
saferax/save.py
saferax/utils.py
saferax-0.0.2.dist-info/LICENSE
saferax-0.0.2.dist-info/METADATA
saferax-0.0.2.dist-info/WHEEL
saferax-0.0.2.dist-info/RECORD
